jobhai_mcp_server/__init__.py
jobhai_mcp_server/__main__.py
jobhai_mcp_server/server.py
jobhai_mcp_server/server_safe.py
jobhai_mcp_server/resources/get_dashboard_data.py
jobhai_mcp_server/resources/get_job_details.py
jobhai_mcp_server-0.2.0.dist-info/METADATA
jobhai_mcp_server-0.2.0.dist-info/WHEEL
jobhai_mcp_server-0.2.0.dist-info/entry_points.txt
jobhai_mcp_server-0.2.0.dist-info/licenses/LICENSE
jobhai_mcp_server-0.2.0.dist-info/RECORD
