Metadata-Version: 2.4
Name: jobhai-mcp-server
Version: 0.2.0
Summary: MCP Server for Job Hai
Project-URL: GitHub, https://github.com/amolsr/jobhai-mcp-server
Project-URL: Issues, https://github.com/amolsr/jobhai-mcp-server/issues
Author-email: Amol Saini <amol.saini567@gmail.com>
License-Expression: MIT
License-File: LICENSE
Requires-Python: >=3.10
Requires-Dist: mcp>=1.6.0
Requires-Dist: openapi-core>=0.19.4
